capture/FceuxStreamCapture.py
capture/NesImageCapture.py
capture/__init__.py
capture/core.py
gamestate/__init__.py
gamestate/models.py
sirtetris/__init__.py
sirtetris/sandbox.py
sirtetris/bot/Bot.py
sirtetris/bot/__init__.py
sirtetris/capture/FceuxStreamCapture.py
sirtetris/capture/NesImageCapture.py
sirtetris/capture/__init__.py
sirtetris/capture/core.py
sirtetris/controller/Controller.py
sirtetris/controller/WindowController.py
sirtetris/controller/__init__.py
sirtetris/gamestate/__init__.py
sirtetris/gamestate/models.py
sirtetris-0.1.6.dist-info/LICENSE
sirtetris-0.1.6.dist-info/METADATA
sirtetris-0.1.6.dist-info/WHEEL
sirtetris-0.1.6.dist-info/top_level.txt
sirtetris-0.1.6.dist-info/RECORD
