Metadata-Version: 2.1
Name: sirtetris
Version: 0.1.6
Summary: Tetris bot engine
Home-page: https://github.com/svencan/sirtetris
Author: Sven Cannivy
Author-email: sven.cannivy@gmail.com
License: UNKNOWN
Platform: UNKNOWN
Classifier: Programming Language :: Python :: 3
Classifier: License :: OSI Approved :: MIT License
Classifier: Operating System :: OS Independent
